compony
